my_cool_project/__init__.py
my_cool_project/main.py
my_cool_project-0.1.0.dist-info/LICENSE
my_cool_project-0.1.0.dist-info/METADATA
my_cool_project-0.1.0.dist-info/WHEEL
my_cool_project-0.1.0.dist-info/top_level.txt
my_cool_project-0.1.0.dist-info/RECORD
