Metadata-Version: 2.1
Name: my-cool-project
Version: 0.1.0
Summary: A simple hello world package from vrutansh...
Home-page: UNKNOWN
Author: Vrutansh
Author-email: vrutansh@test.com
License: MIT
Platform: UNKNOWN
Classifier: Programming Language :: Python :: 3
Classifier: License :: OSI Approved :: MIT License
Classifier: Operating System :: OS Independent
Requires-Python: >=3.6
License-File: LICENSE
